azure/__init__.py
azure/mgmt/__init__.py
azure/mgmt/seabreeze/__init__.py
azure/mgmt/seabreeze/sea_breeze_management_client.py
azure/mgmt/seabreeze/version.py
azure/mgmt/seabreeze/models/__init__.py
azure/mgmt/seabreeze/models/available_operation_display.py
azure/mgmt/seabreeze/models/azure_file_volume.py
azure/mgmt/seabreeze/models/container.py
azure/mgmt/seabreeze/models/container_event.py
azure/mgmt/seabreeze/models/container_group_description.py
azure/mgmt/seabreeze/models/container_group_description_list.py
azure/mgmt/seabreeze/models/container_group_description_paged.py
azure/mgmt/seabreeze/models/container_group_instance_description.py
azure/mgmt/seabreeze/models/container_group_instance_description_list.py
azure/mgmt/seabreeze/models/container_group_properties.py
azure/mgmt/seabreeze/models/container_group_set_description.py
azure/mgmt/seabreeze/models/container_group_set_description_paged.py
azure/mgmt/seabreeze/models/container_instance_view.py
azure/mgmt/seabreeze/models/container_logs.py
azure/mgmt/seabreeze/models/container_port.py
azure/mgmt/seabreeze/models/container_state.py
azure/mgmt/seabreeze/models/environment_variable.py
azure/mgmt/seabreeze/models/error_model.py
azure/mgmt/seabreeze/models/image_registry_credential.py
azure/mgmt/seabreeze/models/ip_address.py
azure/mgmt/seabreeze/models/operation_result.py
azure/mgmt/seabreeze/models/operation_result_paged.py
azure/mgmt/seabreeze/models/proxy_resource.py
azure/mgmt/seabreeze/models/resource.py
azure/mgmt/seabreeze/models/resource_limits.py
azure/mgmt/seabreeze/models/resource_requests.py
azure/mgmt/seabreeze/models/resource_requirements.py
azure/mgmt/seabreeze/models/sea_breeze_management_client_enums.py
azure/mgmt/seabreeze/models/volume.py
azure/mgmt/seabreeze/models/volume_mount.py
azure/mgmt/seabreeze/operations/__init__.py
azure/mgmt/seabreeze/operations/container_group_set_container_logs_operations.py
azure_mgmt_seabreeze-1.0rc1.dist-info/DESCRIPTION.rst
azure_mgmt_seabreeze-1.0rc1.dist-info/METADATA
azure_mgmt_seabreeze-1.0rc1.dist-info/RECORD
azure_mgmt_seabreeze-1.0rc1.dist-info/WHEEL
azure_mgmt_seabreeze-1.0rc1.dist-info/metadata.json
azure_mgmt_seabreeze-1.0rc1.dist-info/top_level.txt
