Metadata-Version: 2.0
Name: azure-mgmt-seabreeze
Version: 1.0rc1
Summary: SeaBreezeManagementClient
Home-page: UNKNOWN
Author: UNKNOWN
Author-email: UNKNOWN
License: UNKNOWN
Keywords: Swagger,SeaBreezeManagementClient
Platform: UNKNOWN
Requires-Dist: msrestazure (>=0.4.7)
